{
    "sender": {
        "email": "brevo@brevo.com",
        "name": "Brevo"
    },
    "subject": "This is my default subject line",
    "templateId": 27,
    "params": {
        "greeting": "This is my default greeting",
        "headline": "This is my default headline"
    },
    "messageVersions": [
        {
            "to": [
                {
                    "email": "bob@example.com",
                    "name": "Bob Anderson"
                },
                {
                    "email": "anne@example.com",
                    "name": "Anne Smith"
                }
            ],
            "params": {
                "greeting": "Welcome onboard!",
                "headline": "Be Ready for Takeoff."
            },
            "subject": "We are happy to be working with you"
        },
        {
            "to": [
                {
                    "email": "jim@example.com",
                    "name": "Jim Stevens"
                },
                {
                    "email": "mark@example.com",
                    "name": "Mark Payton"
                },
                {
                    "email": "andrea@example.com",
                    "name": "Andrea Wallace"
                }
            ],
            "params": {
                "greeting": "Hello there..."
            }
        }
    ]
}